setup.py
GlobalRegisterPlugin.egg-info/PKG-INFO
GlobalRegisterPlugin.egg-info/SOURCES.txt
GlobalRegisterPlugin.egg-info/dependency_links.txt
GlobalRegisterPlugin.egg-info/entry_points.txt
GlobalRegisterPlugin.egg-info/not-zip-safe
GlobalRegisterPlugin.egg-info/top_level.txt
globalregister/__init__.py
globalregister/api.py