Metadata-Version: 1.0
Name: GlobalRegisterPlugin
Version: 0.1.1
Summary: Displays a notice to the user that accounts are shared globally on the server.
Home-page: http://mitar.tnode.com/
Author: Mitar
Author-email: mitar.trac@tnode.com
License: AGPLv3
Keywords: trac plugin
Platform: UNKNOWN
